{
    "movie_info": [
        {
            "Title": "American Psycho",
            "Directed by": "Mary Harron",
            "Screenplay by": [
                "Mary Harron",
                "Guinevere Turner"
            ],
            "Based on": [
                "American Psycho",
                "by",
                "Bret Easton Ellis"
            ],
            "Produced by": [
                "Edward R. Pressman",
                "Chris Hanley",
                "Christian Halsey Solomon"
            ],
            "Starring": [
                "Christian Bale",
                "Willem Dafoe",
                "Jared Leto",
                "Josh Lucas",
                "Samantha Mathis",
                "Matt Ross",
                "Bill Sage",
                "Chloë Sevigny",
                "Cara Seymour",
                "Justin Theroux",
                "Guinevere Turner",
                "Reese Witherspoon"
            ],
            "Cinematography": "Andrzej Sekuła",
            "Edited by": "Andrew Marcus",
            "Music by": "John Cale",
            "Production companies": [
                "Edward R. Pressman Productions",
                "Muse Productions"
            ],
            "Distributed by": [
                "Lions Gate Films",
                "(United States)",
                "Columbia TriStar Film Distributors International",
                "(International)"
            ],
            "Release date": 